libname/__init__.py
libname/add.py
addonalok1210-0.0.6.dist-info/METADATA
addonalok1210-0.0.6.dist-info/WHEEL
addonalok1210-0.0.6.dist-info/top_level.txt
addonalok1210-0.0.6.dist-info/RECORD
