Metadata-Version: 2.1
Name: addonalok1210
Version: 0.0.6
Summary: Basic addition
Home-page: UNKNOWN
Author: Alok Kumar
Author-email: ialok@outlook.com
License: UNKNOWN
Keywords: python,video,stream,video stream,camera stream,sockets
Platform: UNKNOWN
Classifier: Development Status :: 1 - Planning
Classifier: Intended Audience :: Developers
Classifier: Programming Language :: Python :: 3
Classifier: Operating System :: Unix
Classifier: Operating System :: MacOS :: MacOS X
Classifier: Operating System :: Microsoft :: Windows
